lls_trytond_sale_subscription_asset-4.8.1.dist-info/METADATA
lls_trytond_sale_subscription_asset-4.8.1.dist-info/RECORD
lls_trytond_sale_subscription_asset-4.8.1.dist-info/WHEEL
lls_trytond_sale_subscription_asset-4.8.1.dist-info/entry_points.txt
lls_trytond_sale_subscription_asset-4.8.1.dist-info/top_level.txt
trytond/modules/sale_subscription_asset/__init__.py
trytond/modules/sale_subscription_asset/sale.py
trytond/modules/sale_subscription_asset/sale.xml
trytond/modules/sale_subscription_asset/stock.py
trytond/modules/sale_subscription_asset/stock.xml
trytond/modules/sale_subscription_asset/tryton.cfg
trytond/modules/sale_subscription_asset/tests/__init__.py
trytond/modules/sale_subscription_asset/tests/scenario_sale_subscription_asset.rst
trytond/modules/sale_subscription_asset/tests/test_sale_subscription_asset.py
trytond/modules/sale_subscription_asset/view/stock_lot_form.xml
trytond/modules/sale_subscription_asset/view/subscription_line_form.xml
trytond/modules/sale_subscription_asset/view/subscription_line_list.xml
trytond/modules/sale_subscription_asset/view/subscription_service_form.xml
